clockpuncher/__init__.py
clockpuncher/data/example.db
clockpuncher/data/example_project_data.json
clockpuncher/database.py
clockpuncher/fonts/InputMono-Black.ttf
clockpuncher/gui/__init__.py
clockpuncher/gui/base_gui.py
clockpuncher/gui/dev_gui.py
clockpuncher/gui/entry_visualization.py
clockpuncher/gui/menu_settings.py
clockpuncher/gui/timer.py
clockpuncher/main.py
clockpuncher/models.py
clockpuncher/platform_local_storage.py
clockpuncher/tests/__init__.py
clockpuncher/tests/test_database.py
clockpuncher/tests/test_models.py
clockpuncher/tests/test_platform_local_storage.py
clockpuncher/tests/utils.py
clockpuncher-0.1.4.dist-info/entry_points.txt
clockpuncher-0.1.4.dist-info/WHEEL
clockpuncher-0.1.4.dist-info/METADATA
clockpuncher-0.1.4.dist-info/RECORD
