Metadata-Version: 2.1
Name: clockpuncher
Version: 0.1.4
Summary: A hackable GUI time tracker designed to be easily modified for user-centric automation.
License: MIT
Author: Erin Maestas
Author-email: ErinLMaestas@gmail.com
Requires-Python: >=3.7,<4.0
Classifier: License :: OSI Approved :: MIT License
Classifier: Programming Language :: Python :: 3
Classifier: Programming Language :: Python :: 3.10
Classifier: Programming Language :: Python :: 3.7
Classifier: Programming Language :: Python :: 3.8
Classifier: Programming Language :: Python :: 3.9
Requires-Dist: appdirs (>=1.4.4,<2.0.0)
Requires-Dist: dataset (>=1.4.1,<2.0.0)
Requires-Dist: dearpygui (==0.6.415)
Project-URL: homepage, https://github.com/ErinMyLungs/AnalyticStopwatch
Project-URL: issues, https://github.com/ErinMyLungs/AnalyticStopwatch/issues
